structables/__init__.py
structables/config.py
structables/main.py
structables/routes/__init__.py
structables/routes/category.py
structables/routes/contest.py
structables/routes/main.py
structables/routes/member.py
structables/routes/proxy.py
structables/static/css/iframe.css
structables/static/css/style.css
structables/static/img/logo.png
structables/static/img/logo_lg.png
structables/static/img/magnifying-glass-solid.svg
structables/templates/400.html
structables/templates/404.html
structables/templates/429.html
structables/templates/500.html
structables/templates/archives.html
structables/templates/article-review.html
structables/templates/article.html
structables/templates/base.html
structables/templates/category.html
structables/templates/collection.html
structables/templates/contest.html
structables/templates/contests.html
structables/templates/footer.html
structables/templates/header.html
structables/templates/iframe.html
structables/templates/index.html
structables/templates/member-instructables.html
structables/templates/member.html
structables/templates/privacypolicy.html
structables/templates/projects.html
structables/templates/sitemap.html
structables/templates/style.html
structables/utils/data.py
structables/utils/helpers.py
structables-0.4.4.dist-info/METADATA
structables-0.4.4.dist-info/WHEEL
structables-0.4.4.dist-info/entry_points.txt
structables-0.4.4.dist-info/licenses/LICENSE
structables-0.4.4.dist-info/RECORD
