Metadata-Version: 2.4
Name: structables
Version: 0.4.4
Summary: A simple frontend for Instructables
Project-URL: Homepage, https://git.private.coffee/privatecoffee/structables
Project-URL: Bug Tracker, https://git.private.coffee/privatecoffee/structables/issues
Project-URL: Source Code, https://git.private.coffee/privatecoffee/structables
Author-email: "Private.coffee Team" <support@private.coffee>
License:                     GNU AFFERO GENERAL PUBLIC LICENSE
License-File: LICENSE
Classifier: License :: OSI Approved :: GNU Affero General Public License v3
Classifier: Operating System :: OS Independent
Classifier: Programming Language :: Python :: 3
Requires-Python: >=3.10
Requires-Dist: beautifulsoup4
Requires-Dist: flask
Requires-Dist: markdown2[all]
